{"total":11,"rows":[
	{"oid":"1","num":"20130201","username":"二宝","sex":"女","yx":"2班","pro":"计算机专业","phone":"12345678909","email":"3435@qq.com"},
	{"oid":"2","num":"20130202","username":"二宝","sex":"女","yx":"2班","pro":"计算机专业","phone":"12345678909","email":"3435@qq.com"},
	{"oid":"3","num":"20130203","username":"二宝","sex":"女","yx":"2班","pro":"计算机专业","phone":"12345678909","email":"3435@qq.com"},
	{"oid":"4","num":"20130204","username":"二宝","sex":"女","yx":"2班","pro":"计算机专业","phone":"12345678909","email":"3435@qq.com"},
	{"oid":"5","num":"20130205","username":"二宝","sex":"女","yx":"2班","pro":"计算机专业","phone":"12345678909","email":"3435@qq.com"},
	{"oid":"6","num":"20130206","username":"二宝","sex":"女","yx":"2班","pro":"计算机专业","phone":"12345678909","email":"3435@qq.com"},
	{"oid":"7","num":"20130207","username":"二宝","sex":"女","yx":"2班","pro":"计算机专业","phone":"12345678909","email":"3435@qq.com"},
	{"oid":"8","num":"20130208","username":"二宝","sex":"女","yx":"2班","pro":"计算机专业","phone":"12345678909","email":"3435@qq.com"},
	{"oid":"9","num":"20130209","username":"二宝","sex":"女","yx":"2班","pro":"计算机专业","phone":"12345678909","email":"3435@qq.com"},
	{"oid":"10","num":"20130210","username":"二宝","sex":"女","yx":"2班","pro":"计算机专业","phone":"12345678909","email":"3435@qq.com"},
	{"oid":"11","num":"20130211","username":"二宝","sex":"女","yx":"2班","pro":"计算机专业","phone":"12345678909","email":"3435@qq.com"},
	{"oid":"12","num":"20130212","username":"二宝","sex":"女","yx":"2班","pro":"计算机专业","phone":"12345678909","email":"3435@qq.com"},
	{"oid":"13","num":"20130213","username":"二宝","sex":"女","yx":"2班","pro":"计算机专业","phone":"12345678909","email":"3435@qq.com"},
	{"oid":"14","num":"20130214","username":"二宝","sex":"女","yx":"2班","pro":"计算机专业","phone":"12345678909","email":"3435@qq.com"},
	{"oid":"15","num":"20130215","username":"二宝","sex":"女","yx":"2班","pro":"计算机专业","phone":"12345678909","email":"3435@qq.com"},
	{"oid":"16","num":"20130216","username":"二宝","sex":"女","yx":"2班","pro":"计算机专业","phone":"12345678909","email":"3435@qq.com"}
	
]}
